magic_hour/README.md
magic_hour/__init__.py
magic_hour/client.py
magic_hour/environment.py
magic_hour/helpers/__init__.py
magic_hour/helpers/download.py
magic_hour/helpers/logger.py
magic_hour/resources/v1/README.md
magic_hour/resources/v1/__init__.py
magic_hour/resources/v1/ai_clothes_changer/README.md
magic_hour/resources/v1/ai_clothes_changer/__init__.py
magic_hour/resources/v1/ai_clothes_changer/client.py
magic_hour/resources/v1/ai_face_editor/README.md
magic_hour/resources/v1/ai_face_editor/__init__.py
magic_hour/resources/v1/ai_face_editor/client.py
magic_hour/resources/v1/ai_gif_generator/README.md
magic_hour/resources/v1/ai_gif_generator/__init__.py
magic_hour/resources/v1/ai_gif_generator/client.py
magic_hour/resources/v1/ai_headshot_generator/README.md
magic_hour/resources/v1/ai_headshot_generator/__init__.py
magic_hour/resources/v1/ai_headshot_generator/client.py
magic_hour/resources/v1/ai_image_editor/README.md
magic_hour/resources/v1/ai_image_editor/__init__.py
magic_hour/resources/v1/ai_image_editor/client.py
magic_hour/resources/v1/ai_image_generator/README.md
magic_hour/resources/v1/ai_image_generator/__init__.py
magic_hour/resources/v1/ai_image_generator/client.py
magic_hour/resources/v1/ai_image_upscaler/README.md
magic_hour/resources/v1/ai_image_upscaler/__init__.py
magic_hour/resources/v1/ai_image_upscaler/client.py
magic_hour/resources/v1/ai_meme_generator/README.md
magic_hour/resources/v1/ai_meme_generator/__init__.py
magic_hour/resources/v1/ai_meme_generator/client.py
magic_hour/resources/v1/ai_photo_editor/README.md
magic_hour/resources/v1/ai_photo_editor/__init__.py
magic_hour/resources/v1/ai_photo_editor/client.py
magic_hour/resources/v1/ai_qr_code_generator/README.md
magic_hour/resources/v1/ai_qr_code_generator/__init__.py
magic_hour/resources/v1/ai_qr_code_generator/client.py
magic_hour/resources/v1/ai_talking_photo/README.md
magic_hour/resources/v1/ai_talking_photo/__init__.py
magic_hour/resources/v1/ai_talking_photo/client.py
magic_hour-0.47.0.dist-info/LICENSE
magic_hour-0.47.0.dist-info/METADATA
magic_hour-0.47.0.dist-info/WHEEL
magic_hour-0.47.0.dist-info/RECORD
